jp_diet_search/__init__.py
jp_diet_search/cli.py
jp_diet_search/client.py
jp_diet_search/core.py
jp_diet_search/endpoints.py
jp_diet_search/exceptions.py
jp_diet_search/models.py
jp_diet_search/queries.py
jp_diet_search-0.1.1.dist-info/METADATA
jp_diet_search-0.1.1.dist-info/WHEEL
jp_diet_search-0.1.1.dist-info/entry_points.txt
jp_diet_search-0.1.1.dist-info/top_level.txt
jp_diet_search-0.1.1.dist-info/RECORD
