Metadata-Version: 2.4
Name: jp-diet-search
Version: 0.1.1
Summary: Python client & CLI for the National Diet Library Minutes Search API (国会会議録検索システム)
Author-email: Eiichi Yamamoto <info@yeiichi.com>
License: MIT
Project-URL: Homepage, https://kokkai.ndl.go.jp/
Project-URL: Source, https://github.com/yeiichi/jp-diet-search
Keywords: Japan,Diet,Kokkai,National Diet Library,minutes,parliament,API,search
Classifier: License :: OSI Approved :: MIT License
Classifier: Programming Language :: Python :: 3
Classifier: Programming Language :: Python :: 3 :: Only
Classifier: Programming Language :: Python :: 3.10
Classifier: Programming Language :: Python :: 3.11
Classifier: Programming Language :: Python :: 3.12
Classifier: Programming Language :: Python :: 3.13
Classifier: Operating System :: OS Independent
Requires-Python: >=3.10
Requires-Dist: requests>=2.31.0
Requires-Dist: pydantic>=2.7.0
